blyrics.py
interact.py
save.py
search.py
tool.py
web.py
blyrics-1.1.dist-info/DESCRIPTION.rst
blyrics-1.1.dist-info/METADATA
blyrics-1.1.dist-info/RECORD
blyrics-1.1.dist-info/WHEEL
blyrics-1.1.dist-info/metadata.json
blyrics-1.1.dist-info/top_level.txt
