Metadata-Version: 2.0
Name: blyrics
Version: 1.1
Summary: Python client for the GENIUS API -     Also for getting latest articles and charts
Home-page: https://github.com/BlankGodd/BLyrics
Author: Damilare Agbabiaka (BlankGodd)
Author-email: blankgodd33@gmail.com
License: UNKNOWN
Project-URL: Bug Reports, https://github.com/BlankGodd/BLyrics/issues
Project-URL: Read the Docs, https://github.com/BlankGodd/BLyrics/wiki
Keywords: music,lyrics,mp3,music charts,entertainment,genius,articles
Platform: UNKNOWN
Classifier: Environment :: Console
Classifier: Intended Audience :: Developers
Classifier: Natural Language :: English
Classifier: Programming Language :: Python :: 3
Classifier: Programming Language :: Python :: 3.6
Classifier: Programming Language :: Python :: 3.7
Classifier: Programming Language :: Python :: 3.8
Classifier: Programming Language :: Python
Classifier: License :: OSI Approved :: MIT License
Classifier: Operating System :: OS Independent
Classifier: Topic :: Software Development :: Libraries :: Python Modules
Classifier: Topic :: Utilities
Classifier: Topic :: Artistic Software
Classifier: Topic :: Games/Entertainment
Classifier: Topic :: Internet
Classifier: Topic :: Internet :: WWW/HTTP :: Dynamic Content :: Content Management System
Classifier: Topic :: Internet :: WWW/HTTP :: Indexing/Search
Classifier: Topic :: Multimedia :: Sound/Audio
Requires-Python: >=3.6
Requires-Dist: beautifulsoup4 (~=4.9.0)
Requires-Dist: pyfiglet (~=0.8.post1)
Requires-Dist: requests (~=2.21.0)
